cryptocracy/__init__.py
cryptocracy/boundaries/__init__.py
cryptocracy/boundaries/key_authority_service.py
cryptocracy/boundaries/object_store.py
cryptocracy/boundaries/proxy_key_store.py
cryptocracy/delivery/__init__.py
cryptocracy/delivery/cli/__init__.py
cryptocracy/delivery/cli/cryptocracy.py
cryptocracy/model/__init__.py
cryptocracy/model/abe_scheme.py
cryptocracy/model/exceptions.py
cryptocracy/model/key_spec.py
cryptocracy/model/object_cache_lookup_key.py
cryptocracy/model/policy_expression_spec.py
cryptocracy/model/result.py
cryptocracy/model/user_id.py
cryptocracy/use_cases/__init__.py
cryptocracy/use_cases/add_user.py
cryptocracy/use_cases/decrypt_file.py
cryptocracy/use_cases/download_file.py
cryptocracy/use_cases/encrypt_file.py
cryptocracy/use_cases/generate_key_pair.py
cryptocracy/use_cases/list_users.py
cryptocracy/use_cases/register_user.py
cryptocracy/use_cases/revoke_user.py
cryptocracy/use_cases/setup.py
cryptocracy/use_cases/upload_file.py
cryptocracy-0.1.2.dist-info/LICENSE
cryptocracy-0.1.2.dist-info/METADATA
cryptocracy-0.1.2.dist-info/WHEEL
cryptocracy-0.1.2.dist-info/entry_points.txt
cryptocracy-0.1.2.dist-info/top_level.txt
cryptocracy-0.1.2.dist-info/RECORD
