Metadata-Version: 2.1
Name: cryptocracy
Version: 0.1.2
Summary: Client-side attribute-based encryption (ABE)/ access control (ABAC) -
Home-page: https://github.com/doughgle/cryptocracy
Author: Douglas Hellinger
License: UNKNOWN
Platform: UNKNOWN
Requires-Python: >=3.4
Requires-Dist: docopt (>=0.6.2)
Requires-Dist: Flask (>=1.0.2)
Requires-Dist: requests (>=2.21.0)
Requires-Dist: boto3 (>=1.9.111)
